classy_events/__init__.py
classy_events/_utils.py
classy_events/events.py
classy_events/events_threaded.py
classy_events-0.3.4.dist-info/LICENSE
classy_events-0.3.4.dist-info/METADATA
classy_events-0.3.4.dist-info/WHEEL
classy_events-0.3.4.dist-info/top_level.txt
classy_events-0.3.4.dist-info/RECORD
