Metadata-Version: 2.1
Name: classy-events
Version: 0.3.4
Summary: Pythonic event-driven programming.
Home-page: https://github.com/jorenham/classy-events/
Author: Joren Hammudoglu
License: UNKNOWN
Platform: UNKNOWN
Classifier: Intended Audience :: Developers
Classifier: Topic :: Software Development :: Libraries :: Python Modules
Classifier: Programming Language :: Python :: 3
Classifier: License :: OSI Approved :: GNU General Public License v3 (GPLv3)
Classifier: Operating System :: POSIX
Requires-Python: >=3.8.0
Requires-Dist: classy-decorators (==1.0.0)
